{"title":"Multilevel and Marginal Models","markdown":{"yaml":{"title":"Multilevel and Marginal Models","subtitle":"PSY 7650","image":"images/hex_7650.png","about":{"template":"solana","image-shape":"rectangle","image-width":"15em"}},"headingText":"**Focus**","containsRefs":false,"markdown":"\n\nMultilevel Modeling is designed to provide graduate students with a practical, applied approach to the **clustered and/or longitudinal data**. Students will learn how to differentiate and appropriately select the best statistical methods for use in various research designs and analytical problems. This includes Multilevel Modeling (MLM), which also goes by such names as Hierarchical Linear Modeling (HLM) and Mixed Effects Regression (MER), Generalized Multilevel Modeling (GzMLM), and Generalized Estimating Equations (GEE).\n\n\nMastery of the material covered in this course will enable students to develop the skills necessary to conduct well-planned behavioral and educational research involving **clustered or longitudinal designs,** and thoughtful statistical analyses of the resulting data. Knowledge gained in this course will build upon concepts learned in prior research methodology and data analysis courses. Students will learn how to differentiate and appropriately select the best statistical methods for use in various clustered or longitudinal research designs.\n\nAs the theoretical is secondary to the applied approach to data analysis in this course, students will learn how to:\n\n1.  Use the `R` statistical programming environment *(via the `R Studio` IDE)* to analyze **clustered and longitudinal** data and\n\n2.  Interpret and communicate the results of their analyses *(including creating reproducible research reports with R Markdown)*.\n\nThis course will only emphasize methods for manifest or observed, rather than latent or unobserved, variables.\n\n> Successful completion of EDUC/PSY 7610 or an equivalent course in *single level* multiple linear regression is required.\n\n## **Structure**\n\nThis is a lecture and applied skills course and students will be expected to demonstrate their learning via classroom participation, written assignments, and a presentation. Much of the basic material will be presented in readings (textbook and supplements) and pre-recorded lectures which students will view prior to class. The purpose of class time (on Zoom) is to elaborate on interesting or difficult material presented in the text, conduct skill-building exercises and demonstrations, and to provide a forum for class discussions in more of a lab fashion. We will frequently use a hands-on approach in class, working through analyses together via computer software.\n\n## **Syllabus**\n\n-   [Fall 2020 - Dr. Schwartz (Tue/Thr 4:30-6:00 pm)](https://cehs-research.github.io/PSY-7650_public/syllabi/EDUCPSY%206600%20Syllabus%20Sum2020.pdf)\n\n-   [Fall 2020 - Dr. Schwartz (Tue/Thr 4:30-6:00 pm)](https://cehs-research.github.io/PSY-6600_public/syllabi/EDUCPSY%206600%20Syllabus%20Spr2020.pdf)\n\n------------------------------------------------------------------------\n\n# Resources\n\n## Textbooks\n\n1.  **Multilevel Analysis: Techniques and Applications**, 3rd edition (2018), by *Joop J. Hox, Mirjam Moerbeek, and Rens van de Schoot*\n\n-   USU library: [Free, with USU login](https://ebookcentral-proquest-com.dist.lib.usu.edu/lib/usu/reader.action?docID=5046900)\n\n-   Amazon: [purchase, new or used](https://www.amazon.com/Multilevel-Analysis-Quantitative-Methodology-Joop/dp/1138121363/ref=sr_1_1?dchild=1&keywords=*Multilevel+Analysis%3A+Techniques+and+Applications&qid=1599166381&sr=8-1)\n\n2.  **Publication Manual of the APA: The Official Guide to APA Style**, 7th edition (2020)\n\n-   Amazon: [purchase new](https://www.amazon.com/Publication-Manual-American-Psychological-Association-dp-143383216X/dp/143383216X/ref=mt_other?_encoding=UTF8&me=&qid=1599166844)\n\n## Encyclopedia\n\n-   Volume 0. [Setting up Your Computer](https://cehs-research.github.io/eBook_install)\n\n-   Volume 1. [Wrangling Your Data](https://cehs-research.github.io/eBook_wrangle/)\n\n-   Volume 2. [Exploring Your Data](https://cehs-research.github.io/eBook_explore/)\n\n-   Volume 3. [Testing Mean Differences](https://cehs-research.github.io/eBook_ANOVA/)\n\n-   Volume 4. [Correlation & Regression](https://cehs-research.github.io/eBook_regression/)\n\n-   Volume 5. [Multilevel & Marginal Modeling](https://cehs-research.github.io/eBook_multilevel/)\n\n### YouTube\n\n-   Sarah Schwartz Stats [LINK](https://www.youtube.com/channel/UCbkTRp5FeSNIWeueyqBVPkA)\n\n------------------------------------------------------------------------\n\n# OBJECTIVES\n\n1.  Methodological issues in the design of clustered and longitudinal studies\n\n    -   A. Characterize different types of sampling and how they determine analysis type and interpretation\n\n    -   B. Evaluate sample size and power in longitudinal designs\n\n    -   C. Understand the effect of attrition/missing data on results\n\n    -   D. Know what is meant by clustering and how clustered differ from non-clustered analyses\n\n    -   E. Differentiate between long and short data formats\n\n2.  Generalized linear models: Logistic, Poisson, and multinomial regression (GLM)\n\n    -   A. Understand the mathematical fundamentals\n\n    -   B. Know how to properly conduct analyses using R\n\n    -   C. Competently interpret results\n\n3.  Mixed-effects or multi-level longitudinal models (MLM, HLM, ect.)\n\n    -   A. In the context of these methods, define and know how to specify:\n\n        ```         \n        1.  Fixed effects\n\n        2.  Random effects\n\n        3.  Variance components\n\n        4.  Time-varying covariates\n\n        5.  Time-invariant covariates\n\n        6.  Polynomial covariates\n\n        7.  Dummy variables\n\n        8.  Level 1, 2, etc. in multilevel models\n        ```\n\n    -   B. Learn how to use/program R to conduct clustered or longitudinal analyses\n\n    -   C. Interpret output from statistical software in terms of change over time, group differences, individual differences, and change over time as a function of both group or individual differences\n\n4.  Generalized estimating equations (GEE, marginal models)\n\n    -   A. Differentiate between population averaged and subject-specific models\n\n    -   B. Conduct analyses with R\n\n    -   C. Know how to interpret results at the population-averaged or individual level\n\n5.  Competency in use of statistical software (e.g., R and R Studio)\n\n    -   A. Data manipulation\n\n    -   B. Data analysis\n\n    -   C. Interpreting output\n\n    -   D. Graphics\n\n    -   E. R Markdown Reports (Knit to html, pdf, and word)\n\n6.  Develop skills in reporting of statistical results (APA format)\n\n    -   A. Master the basics of communicating results of clustered or longitudinal research\n\n    -   B. Learn how to create tables and figures for presentations\n","srcMarkdownNoYaml":"\n\nMultilevel Modeling is designed to provide graduate students with a practical, applied approach to the **clustered and/or longitudinal data**. Students will learn how to differentiate and appropriately select the best statistical methods for use in various research designs and analytical problems. This includes Multilevel Modeling (MLM), which also goes by such names as Hierarchical Linear Modeling (HLM) and Mixed Effects Regression (MER), Generalized Multilevel Modeling (GzMLM), and Generalized Estimating Equations (GEE).\n\n# **Focus**\n\nMastery of the material covered in this course will enable students to develop the skills necessary to conduct well-planned behavioral and educational research involving **clustered or longitudinal designs,** and thoughtful statistical analyses of the resulting data. Knowledge gained in this course will build upon concepts learned in prior research methodology and data analysis courses. Students will learn how to differentiate and appropriately select the best statistical methods for use in various clustered or longitudinal research designs.\n\nAs the theoretical is secondary to the applied approach to data analysis in this course, students will learn how to:\n\n1.  Use the `R` statistical programming environment *(via the `R Studio` IDE)* to analyze **clustered and longitudinal** data and\n\n2.  Interpret and communicate the results of their analyses *(including creating reproducible research reports with R Markdown)*.\n\nThis course will only emphasize methods for manifest or observed, rather than latent or unobserved, variables.\n\n> Successful completion of EDUC/PSY 7610 or an equivalent course in *single level* multiple linear regression is required.\n\n## **Structure**\n\nThis is a lecture and applied skills course and students will be expected to demonstrate their learning via classroom participation, written assignments, and a presentation. Much of the basic material will be presented in readings (textbook and supplements) and pre-recorded lectures which students will view prior to class. The purpose of class time (on Zoom) is to elaborate on interesting or difficult material presented in the text, conduct skill-building exercises and demonstrations, and to provide a forum for class discussions in more of a lab fashion. We will frequently use a hands-on approach in class, working through analyses together via computer software.\n\n## **Syllabus**\n\n-   [Fall 2020 - Dr. Schwartz (Tue/Thr 4:30-6:00 pm)](https://cehs-research.github.io/PSY-7650_public/syllabi/EDUCPSY%206600%20Syllabus%20Sum2020.pdf)\n\n-   [Fall 2020 - Dr. Schwartz (Tue/Thr 4:30-6:00 pm)](https://cehs-research.github.io/PSY-6600_public/syllabi/EDUCPSY%206600%20Syllabus%20Spr2020.pdf)\n\n------------------------------------------------------------------------\n\n# Resources\n\n## Textbooks\n\n1.  **Multilevel Analysis: Techniques and Applications**, 3rd edition (2018), by *Joop J. Hox, Mirjam Moerbeek, and Rens van de Schoot*\n\n-   USU library: [Free, with USU login](https://ebookcentral-proquest-com.dist.lib.usu.edu/lib/usu/reader.action?docID=5046900)\n\n-   Amazon: [purchase, new or used](https://www.amazon.com/Multilevel-Analysis-Quantitative-Methodology-Joop/dp/1138121363/ref=sr_1_1?dchild=1&keywords=*Multilevel+Analysis%3A+Techniques+and+Applications&qid=1599166381&sr=8-1)\n\n2.  **Publication Manual of the APA: The Official Guide to APA Style**, 7th edition (2020)\n\n-   Amazon: [purchase new](https://www.amazon.com/Publication-Manual-American-Psychological-Association-dp-143383216X/dp/143383216X/ref=mt_other?_encoding=UTF8&me=&qid=1599166844)\n\n## Encyclopedia\n\n-   Volume 0. [Setting up Your Computer](https://cehs-research.github.io/eBook_install)\n\n-   Volume 1. [Wrangling Your Data](https://cehs-research.github.io/eBook_wrangle/)\n\n-   Volume 2. [Exploring Your Data](https://cehs-research.github.io/eBook_explore/)\n\n-   Volume 3. [Testing Mean Differences](https://cehs-research.github.io/eBook_ANOVA/)\n\n-   Volume 4. [Correlation & Regression](https://cehs-research.github.io/eBook_regression/)\n\n-   Volume 5. [Multilevel & Marginal Modeling](https://cehs-research.github.io/eBook_multilevel/)\n\n### YouTube\n\n-   Sarah Schwartz Stats [LINK](https://www.youtube.com/channel/UCbkTRp5FeSNIWeueyqBVPkA)\n\n------------------------------------------------------------------------\n\n# OBJECTIVES\n\n1.  Methodological issues in the design of clustered and longitudinal studies\n\n    -   A. Characterize different types of sampling and how they determine analysis type and interpretation\n\n    -   B. Evaluate sample size and power in longitudinal designs\n\n    -   C. Understand the effect of attrition/missing data on results\n\n    -   D. Know what is meant by clustering and how clustered differ from non-clustered analyses\n\n    -   E. Differentiate between long and short data formats\n\n2.  Generalized linear models: Logistic, Poisson, and multinomial regression (GLM)\n\n    -   A. Understand the mathematical fundamentals\n\n    -   B. Know how to properly conduct analyses using R\n\n    -   C. Competently interpret results\n\n3.  Mixed-effects or multi-level longitudinal models (MLM, HLM, ect.)\n\n    -   A. In the context of these methods, define and know how to specify:\n\n        ```         \n        1.  Fixed effects\n\n        2.  Random effects\n\n        3.  Variance components\n\n        4.  Time-varying covariates\n\n        5.  Time-invariant covariates\n\n        6.  Polynomial covariates\n\n        7.  Dummy variables\n\n        8.  Level 1, 2, etc. in multilevel models\n        ```\n\n    -   B. Learn how to use/program R to conduct clustered or longitudinal analyses\n\n    -   C. Interpret output from statistical software in terms of change over time, group differences, individual differences, and change over time as a function of both group or individual differences\n\n4.  Generalized estimating equations (GEE, marginal models)\n\n    -   A. Differentiate between population averaged and subject-specific models\n\n    -   B. Conduct analyses with R\n\n    -   C. Know how to interpret results at the population-averaged or individual level\n\n5.  Competency in use of statistical software (e.g., R and R Studio)\n\n    -   A. Data manipulation\n\n    -   B. Data analysis\n\n    -   C. Interpreting output\n\n    -   D. Graphics\n\n    -   E. R Markdown Reports (Knit to html, pdf, and word)\n\n6.  Develop skills in reporting of statistical results (APA format)\n\n    -   A. Master the basics of communicating results of clustered or longitudinal research\n\n    -   B. Learn how to create tables and figures for presentations\n"},"formats":{"html":{"identifier":{"display-name":"HTML","target-format":"html","base-format":"html"},"execute":{"fig-width":7,"fig-height":5,"fig-format":"retina","fig-dpi":96,"df-print":"default","error":false,"eval":true,"cache":null,"freeze":"auto","echo":true,"output":true,"warning":true,"include":true,"keep-md":false,"keep-ipynb":false,"ipynb":null,"enabled":null,"daemon":null,"daemon-restart":false,"debug":false,"ipynb-filters":[],"ipynb-shell-interactivity":null,"plotly-connected":true,"engine":"markdown"},"render":{"keep-tex":false,"keep-typ":false,"keep-source":false,"keep-hidden":false,"prefer-html":false,"output-divs":true,"output-ext":"html","fig-align":"default","fig-pos":null,"fig-env":null,"code-fold":"none","code-overflow":"scroll","code-link":false,"code-line-numbers":false,"code-tools":false,"tbl-colwidths":"auto","merge-includes":true,"inline-includes":false,"preserve-yaml":false,"latex-auto-mk":true,"latex-auto-install":true,"latex-clean":true,"latex-min-runs":1,"latex-max-runs":10,"latex-makeindex":"makeindex","latex-makeindex-opts":[],"latex-tlmgr-opts":[],"latex-input-paths":[],"latex-output-dir":null,"link-external-icon":false,"link-external-newwindow":false,"self-contained-math":false,"format-resources":[],"notebook-links":true},"pandoc":{"standalone":true,"wrap":"none","default-image-extension":"png","to":"html","css":["styles.css"],"toc":true,"output-file":"mlm.html"},"language":{"toc-title-document":"Table of contents","toc-title-website":"On this page","related-formats-title":"Other Formats","related-notebooks-title":"Notebooks","source-notebooks-prefix":"Source","other-links-title":"Other Links","code-links-title":"Code Links","launch-dev-container-title":"Launch Dev Container","launch-binder-title":"Launch Binder","article-notebook-label":"Article Notebook","notebook-preview-download":"Download Notebook","notebook-preview-download-src":"Download Source","notebook-preview-back":"Back to Article","manuscript-meca-bundle":"MECA Bundle","section-title-abstract":"Abstract","section-title-appendices":"Appendices","section-title-footnotes":"Footnotes","section-title-references":"References","section-title-reuse":"Reuse","section-title-copyright":"Copyright","section-title-citation":"Citation","appendix-attribution-cite-as":"For attribution, please cite this work as:","appendix-attribution-bibtex":"BibTeX citation:","appendix-view-license":"View License","title-block-author-single":"Author","title-block-author-plural":"Authors","title-block-affiliation-single":"Affiliation","title-block-affiliation-plural":"Affiliations","title-block-published":"Published","title-block-modified":"Modified","title-block-keywords":"Keywords","callout-tip-title":"Tip","callout-note-title":"Note","callout-warning-title":"Warning","callout-important-title":"Important","callout-caution-title":"Caution","code-summary":"Code","code-tools-menu-caption":"Code","code-tools-show-all-code":"Show All Code","code-tools-hide-all-code":"Hide All Code","code-tools-view-source":"View Source","code-tools-source-code":"Source Code","tools-share":"Share","tools-download":"Download","code-line":"Line","code-lines":"Lines","copy-button-tooltip":"Copy to Clipboard","copy-button-tooltip-success":"Copied!","repo-action-links-edit":"Edit this page","repo-action-links-source":"View source","repo-action-links-issue":"Report an issue","back-to-top":"Back to top","search-no-results-text":"No results","search-matching-documents-text":"matching documents","search-copy-link-title":"Copy link to search","search-hide-matches-text":"Hide additional matches","search-more-match-text":"more match in this document","search-more-matches-text":"more matches in this document","search-clear-button-title":"Clear","search-text-placeholder":"","search-detached-cancel-button-title":"Cancel","search-submit-button-title":"Submit","search-label":"Search","toggle-section":"Toggle section","toggle-sidebar":"Toggle sidebar navigation","toggle-dark-mode":"Toggle dark mode","toggle-reader-mode":"Toggle reader mode","toggle-navigation":"Toggle navigation","crossref-fig-title":"Figure","crossref-tbl-title":"Table","crossref-lst-title":"Listing","crossref-thm-title":"Theorem","crossref-lem-title":"Lemma","crossref-cor-title":"Corollary","crossref-prp-title":"Proposition","crossref-cnj-title":"Conjecture","crossref-def-title":"Definition","crossref-exm-title":"Example","crossref-exr-title":"Exercise","crossref-ch-prefix":"Chapter","crossref-apx-prefix":"Appendix","crossref-sec-prefix":"Section","crossref-eq-prefix":"Equation","crossref-lof-title":"List of Figures","crossref-lot-title":"List of Tables","crossref-lol-title":"List of Listings","environment-proof-title":"Proof","environment-remark-title":"Remark","environment-solution-title":"Solution","listing-page-order-by":"Order By","listing-page-order-by-default":"Default","listing-page-order-by-date-asc":"Oldest","listing-page-order-by-date-desc":"Newest","listing-page-order-by-number-desc":"High to Low","listing-page-order-by-number-asc":"Low to High","listing-page-field-date":"Date","listing-page-field-title":"Title","listing-page-field-description":"Description","listing-page-field-author":"Author","listing-page-field-filename":"File Name","listing-page-field-filemodified":"Modified","listing-page-field-subtitle":"Subtitle","listing-page-field-readingtime":"Reading Time","listing-page-field-wordcount":"Word Count","listing-page-field-categories":"Categories","listing-page-minutes-compact":"{0} min","listing-page-category-all":"All","listing-page-no-matches":"No matching items","listing-page-words":"{0} words","listing-page-filter":"Filter","draft":"Draft"},"metadata":{"lang":"en","fig-responsive":true,"quarto-version":"1.5.57","editor":"visual","theme":"zephyr","title":"Multilevel and Marginal Models","subtitle":"PSY 7650","image":"images/hex_7650.png","about":{"template":"solana","image-shape":"rectangle","image-width":"15em"}},"extensions":{"book":{"multiFile":true}}}},"projectFormats":["html"]}